secrank/__init__.py
secrank/apiutils.py
secrank/cli.py
secrank/exceptions.py
secrank/logger.py
secrank/pdns.py
secrank/trends.py
secrank/whois.py
secrank-1.1.0.dist-info/METADATA
secrank-1.1.0.dist-info/WHEEL
secrank-1.1.0.dist-info/entry_points.txt
secrank-1.1.0.dist-info/top_level.txt
secrank-1.1.0.dist-info/RECORD
