Metadata-Version: 2.1
Name: secrank
Version: 1.1.0
Summary: Python library and command-line tool for SecRank (https://secrank.com)
Home-page: https://github.com/SecRank/secrank-api
Author: iliwoy
Author-email: iliwoy@gmail.com
License: UNKNOWN
Keywords: security tool,secrank,command tool
Platform: UNKNOWN
Classifier: Development Status :: 5 - Production/Stable
Classifier: Intended Audience :: Developers
Classifier: License :: OSI Approved :: MIT License
Classifier: Natural Language :: English
Classifier: Operating System :: OS Independent
Classifier: Programming Language :: Python :: 3
Classifier: Programming Language :: Python :: 3.5
Classifier: Programming Language :: Python :: 3.6
Classifier: Programming Language :: Python :: 3.7
Classifier: Programming Language :: Python :: 3.8
Classifier: Programming Language :: Python :: 3.9
Classifier: Topic :: Software Development :: Libraries :: Python Modules
Requires-Dist: argparse
Requires-Dist: pandas
Requires-Dist: plotext
Requires-Dist: requests
